{
  "exam_info": {
    "title": "2024年4月高等教育自学考试全国统一命题考试",
    "subject": "公文写作与处理",
    "code": "00341",
    "date": "2024-04"
  },
  "questions": [
    {
      "question_number": "1",
      "question_type": "单项选择题",
      "content": "下列文件标题，应居于公文首页中部的是",
      "options": {
        "A": "附件",
        "B": "标题",
        "C": "公文",
        "D": "正文"
      },
      "answer": "B",
      "score": 1
    },
    {
      "question_number": "2",
      "question_type": "单项选择题",
      "content": "机关的信笺、名信片、直邮件为政府的公文",
      "options": {
        "A": "报告",
        "B": "公函",
        "C": "行文",
        "D": "下行文"
      },
      "answer": "D",
      "score": 1
    },
    {
      "question_number": "3",
      "question_type": "单项选择题",
      "content": "关于我国现行公文包括公文的文种有",
      "options": {
        "A": "12种",
        "B": "13种",
        "C": "15种",
        "D": "14种"
      },
      "answer": "A",
      "score": 1
    },
    {
      "question_number": "4",
      "question_type": "单项选择题",
      "content": "发文机关单位是同级、互相没有隶属关系的，公文的行文方式为",
      "options": {
        "A": "下行文",
        "B": "平行文",
        "C": "顺行文",
        "D": "上行文"
      },
      "answer": "D",
      "score": 1
    },
    {
      "question_number": "5",
      "question_type": "单项选择题",
      "content": "公文处理的最后程序是",
      "options": {
        "A": "发文",
        "B": "传阅",
        "C": "归档",
        "D": "催办"
      },
      "answer": "A",
      "score": 1
    },
    {
      "question_number": "6",
      "question_type": "单项选择题",
      "content": "XX 单位 XX 年度统计报表送达通知 该通知属于",
      "options": {
        "A": "命令",
        "B": "批复",
        "C": "通报",
        "D": "通知"
      },
      "answer": "D",
      "score": 1
    },
    {
      "question_number": "7",
      "question_type": "单项选择题",
      "content": "公文写作与处理试题试题第1页（共5页）",
      "options": {
        "A": "无",
        "B": "无",
        "C": "无",
        "D": "无"
      },
      "answer": "A",
      "score": 1
    },
    {
      "question_number": "8",
      "question_type": "单项选择题",
      "content": "党中央信省省省委之间的平行文关系是",
      "options": {
        "A": "同一系统领导与隶属关系",
        "B": "上下级机关主管部门业务指导的平级关系",
        "C": "非垂直领导的隶属关系",
        "D": "同一系统的平行关系"
      },
      "answer": "A",
      "score": 1
    },
    {
      "question_number": "9",
      "question_type": "单项选择题",
      "content": "党领导机关的下行文方式是",
      "options": {
        "A": "遴选下行文",
        "B": "多级下行文",
        "C": "直接送知照",
        "D": "总领导下行文"
      },
      "answer": "C",
      "score": 1
    },
    {
      "question_number": "10",
      "question_type": "单项选择题",
      "content": "关于机关发出的具有时效要求的通知，受权发布的是",
      "options": {
        "A": "特别紧急通知",
        "B": "批复",
        "C": "临时业务部门",
        "D": "机关办公室"
      },
      "answer": "B",
      "score": 1
    },
    {
      "question_number": "11",
      "question_type": "单项选择题",
      "content": "以下公文中不需要发文字号的文件是",
      "options": {
        "A": "公文",
        "B": "议案",
        "C": "决议",
        "D": "公告"
      },
      "answer": "B",
      "score": 1
    },
    {
      "question_number": "12",
      "question_type": "单项选择题",
      "content": "下列文件决定的主要特点是",
      "options": {
        "A": "政策性强",
        "B": "灵活性强",
        "C": "一般事项",
        "D": "一般事项"
      },
      "answer": "A",
      "score": 1
    },
    {
      "question_number": "13",
      "question_type": "单项选择题",
      "content": "通报的接受对象是属同级和",
      "options": {
        "A": "直属",
        "B": "级联性",
        "C": "兄弟关系",
        "D": "指导性"
      },
      "answer": "D",
      "score": 1
    },
    {
      "question_number": "14",
      "question_type": "单项选择题",
      "content": "表在通知标题的属性问题，标题应选项为",
      "options": {
        "A": "转发……关于……的通知和通知",
        "B": "关于……的指通知",
        "C": "关于……的通知",
        "D": "关于……的通知"
      },
      "answer": "C",
      "score": 1
    },
    {
      "question_number": "15",
      "question_type": "单项选择题",
      "content": "表在通知书中介绍公文注意的写作要求是",
      "options": {
        "A": "标题居中",
        "B": "标题加粗",
        "C": "简明表述，突出现实意义，撰稿人部分",
        "D": "简明表述，注重条理性"
      },
      "answer": "B",
      "score": 1
    },
    {
      "question_number": "16",
      "question_type": "单项选择题",
      "content": "报告知识的写作类型，一类是请求式报告，另一类是",
      "options": {
        "A": "典型性",
        "B": "合议性",
        "C": "案卷类型",
        "D": "事项报告"
      },
      "answer": "C",
      "score": 1
    },
    {
      "question_number": "17",
      "question_type": "单项选择题",
      "content": "不得越级发文是公文间人员调动时文，应该用的文件是",
      "options": {
        "A": "命令",
        "B": "决定",
        "C": "通知",
        "D": "通告"
      },
      "answer": "B",
      "score": 1
    },
    {
      "question_number": "18",
      "question_type": "单项选择题",
      "content": "会计规范与财务部门拟发出的法定公文文书年限为",
      "options": {
        "A": "1951年",
        "B": "1981年",
        "C": "近年",
        "D": "1989年"
      },
      "answer": "C",
      "score": 1
    },
    {
      "question_number": "19",
      "question_type": "单项选择题",
      "content": "计划规定书与规范型类文书拟出，其实现目的的期限限定，一般期限为",
      "options": {
        "A": "1年以内",
        "B": "1~2年",
        "C": "2~3年",
        "D": "5年以上"
      },
      "answer": "A",
      "score": 1
    },
    {
      "question_number": "20",
      "question_type": "单项选择题",
      "content": "制定实施细则的目的是加强整体性、规范的",
      "options": {
        "A": "规范性",
        "B": "强制性",
        "C": "程序性",
        "D": "可靠性"
      },
      "answer": "D",
      "score": 1
    },
    {
      "question_number": "21",
      "question_type": "单项选择题",
      "content": "为专门有用和现代化做适应个体规定的行文，是",
      "options": {
        "A": "命令",
        "B": "方针",
        "C": "建议",
        "D": "办法"
      },
      "answer": "D",
      "score": 1
    },
    {
      "question_number": "22",
      "question_type": "单项选择题",
      "content": "公文处理工作对机关工作的作用，具有留存和保障",
      "options": {
        "A": "领导作用",
        "B": "标准作用",
        "C": "行政作用",
        "D": "审查作用"
      },
      "answer": "C",
      "score": 1
    },
    {
      "question_number": "23",
      "question_type": "单项选择题",
      "content": "机关制发呈报类型具有",
      "options": {
        "A": "领导性",
        "B": "创新性",
        "C": "预报性",
        "D": "激励性"
      },
      "answer": "C",
      "score": 1
    },
    {
      "question_number": "24",
      "question_type": "单项选择题",
      "content": "开展总结性、微观性和评估性的讲话类文书把",
      "options": {
        "A": "议论性",
        "B": "评审意见",
        "C": "开场白",
        "D": "审议性"
      },
      "answer": "D",
      "score": 1
    },
    {
      "question_number": "25",
      "question_type": "单项选择题",
      "content": "近期领导人对各级工作人员非常重视，提出“要建立聘期、密接监督保安全、保发展”的领导意见",
      "options": {
        "A": "就业期",
        "B": "聘期",
        "C": "晋级",
        "D": "补岗制"
      },
      "answer": "C",
      "score": 1
    },
    {
      "question_number": "26",
      "question_type": "单项选择题",
      "content": "批转类是再规范的文书常用类别，为确保公文效果",
      "options": {
        "A": "准确、高度、确保质量",
        "B": "及时、迅速、注重时效",
        "C": "精确方案，反复对主体定义",
        "D": "精确方案，创新文书处理"
      },
      "answer": "B",
      "score": 1
    },
    {
      "question_number": "27",
      "question_type": "单项选择题",
      "content": "某县人民医院公布发生工作的组织形式类型是",
      "options": {
        "A": "集中形式",
        "B": "分工处理形式",
        "C": "外包形式",
        "D": "联合制度"
      },
      "answer": "A",
      "score": 1
    },
    {
      "question_number": "28",
      "question_type": "单项选择题",
      "content": "收发处理是岗位的写作要求",
      "options": {
        "A": "马列主义教育计划",
        "B": "秘密详细研究方案",
        "C": "文字稿、题目的合理由",
        "D": "材料标本，连通文文书"
      },
      "answer": "C",
      "score": 1
    },
    {
      "question_number": "29",
      "question_type": "单项选择题",
      "content": "下列属于应答类的文书是",
      "options": {
        "A": "上级机关的文件材料",
        "B": "一般性工作的答函",
        "C": "公司规程",
        "D": "规章文件形表现"
      },
      "answer": "A",
      "score": 1
    },
    {
      "question_number": "30",
      "question_type": "单项选择题",
      "content": "召开承诺大会会议通知、日程安排、会议议程，会议纪要等文件按“件”进行标识。",
      "options": {
        "A": "议程、阶段文件类型原则",
        "B": "会议流程化形成规范",
        "C": "便于保留",
        "D": "便于利用"
      },
      "answer": "B",
      "score": 1
    },
    {
      "question_number": "31",
      "question_type": "多项选择题",
      "content": "关于领导职能及其在公文行",
      "options": {
        "A": "法定的作用",
        "B": "法定的权威",
        "C": "法定的职责",
        "D": "行政的特点",
        "E": "规范的程序"
      },
      "answer": "ABCDE",
      "score": 2
    },
    {
      "question_number": "32",
      "question_type": "多项选择题",
      "content": "公文的实施过程，允许表象下机关的",
      "options": {
        "A": "业务水平",
        "B": "事务水平",
        "C": "党委政策",
        "D": "行政职能",
        "E": "领导水平"
      },
      "answer": "ABC",
      "score": 2
    },
    {
      "question_number": "33",
      "question_type": "多项选择题",
      "content": "下列通和标准形式正确的有",
      "options": {
        "A": "发文单位加大中",
        "B": "事由加文件",
        "C": "发文单位加文种",
        "D": "只写字号名称"
      },
      "answer": "BDE",
      "score": 2
    },
    {
      "question_number": "34",
      "question_type": "多项选择题",
      "content": "拟写的写作要点有",
      "options": {
        "A": "职责要素要准确",
        "B": "事项要具有创新性",
        "C": "问题成效要充分深入",
        "D": "表达规范和鲜明",
        "E": "适宜创新型逻辑结构"
      },
      "answer": "ADE",
      "score": 2
    },
    {
      "question_number": "35",
      "question_type": "多项选择题",
      "content": "主要领导的担任的公文件签署重要性工作的有",
      "options": {
        "A": "注重文件价值创新",
        "B": "更新观念，增强效率意识",
        "C": "推动信息化",
        "D": "重视管理转变",
        "E": "注重新标准方法"
      },
      "answer": "BCDE",
      "score": 2
    },
    {
      "question_number": "36",
      "question_type": "简答题",
      "content": "简述通用类文件的组成部分。",
      "answer": "(1) 公文标题（1分） (2) 主送机关（1分） (3) 公文正文（1分） (4) 附件、成文时间（1分） (5) 公文生效标识、附注（1分）",
      "score": 5
    },
    {
      "question_number": "37",
      "question_type": "简答题",
      "content": "简述公文种类的内容。",
      "answer": "(1) 正本（1分） (2) 副本（1分） (3) 存本（1分） (4) 修订本（1分） (5) 试行本、暂行本、各种文字文本（1分）",
      "score": 5
    },
    {
      "question_number": "38",
      "question_type": "简答题",
      "content": "简述公文的行文方式和行文方式。",
      "answer": "行文方向：上行、下行、平行（2分） 行文方式：上行文（1分）、下行文（1分）、平行文（1分）",
      "score": 5
    },
    {
      "question_number": "39",
      "question_type": "简答题",
      "content": "简述档案文件案卷组卷的理由。",
      "answer": "按事由排列，遵循了文件形成的客观规律，能够保持文件之间的有机联系（2分），使归档文件进一步系统化（1分）充分体现文件的价值（1分）、便于查索和利用（1分）",
      "score": 5
    },
    {
      "question_number": "40",
      "question_type": "简答题",
      "content": "简述档案文件的目录项目。",
      "answer": "(1) 全宗名称（2分） (2) 年度（1分） (3) 保管期限（1分） (4) 机构（问题）（1分）",
      "score": 5
    },
    {
      "question_number": "41",
      "question_type": "论述题",
      "content": "试述公告与通告的差异及举例。",
      "answer": "(1) 发布的公开性。公告与通告内容都是公开的，但发布的范围不同。公告涉及范围广，通告涉及范围小。如果处理地区内部事务的通告，标不必要刻意地张贴。（4分） (2) 事项的重要性。必须是重要事项才使用公告与通告发布。各公告较重大事务，通告公布事项更便次于公告。（3分） (3) 操作的严谨性。公告与通告内容要涉及面广，操作必须严密。公告一般由国家或政府机构发布，一般机关团体不能随意发布公告。发通告也要注意权限制，不能随意发布。（3分）",
      "score": 10
    },
    {
      "question_number": "42",
      "question_type": "论述题",
      "content": "论述会议纪要的意义及写作特点。",
      "answer": "(1) 会议纪要的特点有：纪要性、约束性和规则性。（3分） (2) 会议纪要的写作一般在会议结束时，经主管领导人签字同意或计票表决通过。（2分） 会议纪要的标题常用“会议名称加文种”，也可省名“会议”二字。（1分） 会议纪要正文一般分为会议概况、会议内容、结语或三部分。（3分） 会议纪要要点以主持机关撰写。（1分）",
      "score": 10
    },
    {
      "question_number": "43",
      "question_type": "综合应用题",
      "content": "试根据下面材料，回答公文处理相关问题。\n\n材料：\n2022年X月X日，XX市人民政府办公室将所有新发布的政府规范性文件清理及废止有关安排发了一个通知，办公室从XX县人民政府关于2021年规范性文件清理及废止情况的请示报告，经县政府相关部门审核后，将清理工作方案、废止的市政府规范性文件、相关目录等资料经县长签字审核后上报市政府，现将清理结果发布如下。\n附件：1.继续实施的市政府规范性文件目录\n       2.废止和失效的市政府规范性文件目录\n\nXX市人民政府办公室\n2022年5月27日\n\n问题：\n（1）请从发文办理程序回答，该市政府办公室要收到发文并发布本通知，必须做好哪些环节工作？其中哪个环节最重要，说明理由。\n\n（2）假如你是县政府所属政府的办公室文员，收到上级这个通知文件，你应如何办理收文工作？收文办理程序有哪些环节工作？",
      "answer": "(1) 发文办理程序包括：拟稿、审核与签发、核发、缮印与校对、用印、登记与分发组成，发文必须做好每一环节工作（3分）\n其中最重要的环节是第一步：公文的拟稿，是整个公文处理的关键性工作之一（1分）。公文拟稿，是公文承办人员根据领导交办，或其他的意见进行文稿的过程。（1分）。公文拟稿是传达定作者的应当，体现机关领导意图和愿望的写作活动，需要文单位的积 妥理解执行，直接影响公文的工作效率。所以，公文拟稿是发文办理中最重要环节（2分）。\n\n(2) 收文办理，指文件部门收到文件材料后，在机关内部及相关部门运转直至收到办完毕的全过程（2分）。组织这一过程的一系列相互衔接的环节称之为收文办理程序。（1分）具体内容包括：\n① 签收、拆封和登记。（2分）\n② 审核分发和传阅。（1分）\n③ 拟办、批办和承办。（1分）\n④ 催办、查办与注销。（1分）",
      "score": 15
    }
  ]
}